CHANGELOG.md
README.rst
tg_bw_helper/__init__.py
tg_bw_helper/__main__.py
tg_bw_helper/bw_client.py
tg_bw_helper/tests/conftest.py
tg_bw_helper/tests/fake-bw-failing-master-password.py
tg_bw_helper/tests/fake-bw-not-logged-in.py
tg_bw_helper/tests/fake-bw-unknown-error.py
tg_bw_helper/tests/fake-bw.py
tg_bw_helper/tests/fake-which.py
tg_bw_helper/tests/test_arguments.py
tg_bw_helper/tests/test_bw_cli_fails.py
tg_bw_helper/tests/test_get_password.py
tg_bw_helper-1.0.2.dist-info/entry_points.txt
tg_bw_helper-1.0.2.dist-info/WHEEL
tg_bw_helper-1.0.2.dist-info/METADATA
tg_bw_helper-1.0.2.dist-info/RECORD
