Metadata-Version: 2.1
Name: tg-bw-helper
Version: 1.0.2
Summary: Thorgate helper for ansible vault password
Home-page: https://thorgate.eu
Author: Sergey Kovalskiy
Author-email: sergey@thorgate.eu
Requires-Python: >=3.8,<4.0
Classifier: Intended Audience :: Developers
Classifier: Operating System :: POSIX
Classifier: Programming Language :: Python
Classifier: Programming Language :: Python :: 3
Classifier: Programming Language :: Python :: 3 :: Only
Classifier: Programming Language :: Python :: 3.10
Classifier: Programming Language :: Python :: 3.8
Classifier: Programming Language :: Python :: 3.9
Project-URL: Bug Tracker, https://gitlab.com/thorgate-public/tg-bw-helper/-/issues
Project-URL: Changelog, https://gitlab.com/thorgate-public/tg-bw-helper/-/blob/master/CHANGELOG.md
Project-URL: Source Code, https://gitlab.com/thorgate-public/tg-bw-helper
